Metadata-Version: 2.1
Name: autora-experimentalist-novelty
Version: 2.2.0
Summary: AutoRA Novelty Experimentalist
Author-email: Sebastian Musslick <sebastian@musslick.de>
License: MIT License
Project-URL: homepage, http://www.empiricalresearch.ai
Project-URL: repository, https://github.com/AutoResearch/autora-experimentalist-novelty
Project-URL: documentation, https://autoresearch.github.io/autora/
Requires-Python: <4,>=3.8.10
License-File: LICENSE
Requires-Dist: autora-core >=3.1.0
Provides-Extra: dev
Requires-Dist: autora-core[dev] ; extra == 'dev'
